drf_tmp_scoped_token-0.2.1.dist-info/DESCRIPTION.rst
drf_tmp_scoped_token-0.2.1.dist-info/METADATA
drf_tmp_scoped_token-0.2.1.dist-info/RECORD
drf_tmp_scoped_token-0.2.1.dist-info/WHEEL
drf_tmp_scoped_token-0.2.1.dist-info/metadata.json
drf_tmp_scoped_token-0.2.1.dist-info/top_level.txt
rest_framework_tmp_scoped_token/__init__.py
rest_framework_tmp_scoped_token/auth.py
rest_framework_tmp_scoped_token/token.py
tests/__init__.py
tests/manage.py
tests/settings.py
tests/test_app/__init__.py
tests/test_app/tests.py
