Metadata-Version: 2.0
Name: drf-tmp-scoped-token
Version: 0.2.1
Summary: Temporary Django REST Framework permission-scoped token
Home-page: https://github.com/Cadasta/drf-tmp-scoped-token
Author: Anthony Lukach
Author-email: alukach@cadasta.org
License: GNU Affero General Public License v3.0
Platform: UNKNOWN
Classifier: Development Status :: 3 - Alpha
Requires-Dist: djangorestframework (>=3.4.0)
Requires-Dist: six
